Workbook

Sheet Read Me
B2: NHS Cheshire & Merseyside — Elective Capacity Optimizer
B4: Objective
B5: Minimize the total forecasted number of RTT incomplete pathways waiting over 52 weeks, summed across the 12 core Cheshire & Merseyside trusts, over the 18-month forecast horizon (2026-04-01 to 2027-09-01).
B7: Decision variables
B8: 36 cells (12 providers x 3 levers): additional monthly in-house elective capacity, independent-sector outsourcing, and diagnostic capacity investment, each expressed in RTT-equivalent completed pathways/month so the three levers are directly comparable. See the 'Solver Model' tab.
B10: Grain decision
B11: Decision variables sit at PROVIDER level, not provider-specialty. Two of the three capacity-ceiling data sources (NHS Workforce Statistics, KH03 bed occupancy) only exist at provider grain in the underlying warehouse — there is no specialty-level FTE or bed data to constrain against — so a genuinely specialty-disaggregated model isn't supportable by the data actually available, independent of Excel's Solver also having a practical ~200-variable ceiling that a 12 x ~20-specialty x 3-lever model would exceed anyway.
B13: Constraints
B14: (1) Total cost <= budget envelope (an adjustable scenario input, not an asserted real ICB budget — see Assumptions tab); (2) each lever capped per provider by workforce/bed headroom or current activity growth rate; (3) independent-sector cap bounded by the ICB's current real outsourcing volume; (4) a BOUNDED equity tolerance — higher-deprivation providers must receive at least their baseline breach share minus 15 percentage points, not a hard no-worsening floor. All four per Vedant's confirmed design, docs/STATUS.md, 2026-08-07.
B16: How to use this workbook
B17: The 'Solver Model' tab is pre-filled with a Python-validated reference-optimal solution (scipy.optimize.linprog, HiGHS solver) for the default £15m budget scenario. Every decision cell (blue, columns I:K) is live and Solver-ready — change the budget or any Assumption and re-run Excel's own Solver (Data > Solver) to re-optimize; exact cell references are on the 'Solver Model' tab itself.
B19: What's genuinely sourced vs. estimated
... B23: With in-house and outsourcing now correctly priced EQUALLY (both £472/unit, following the 2025/26 payment-scheme correction above), the earlier 'outsourcing only activates once in-house is also full' story simplifies further: at any budget where both levers have spare capacity, the model is genuinely indifferent between them — Solver will fill whichever has capacity headroom left, not prefer one on cost grounds. Diagnostics (£247/unit) still fills first since it's structurally cheaper. The 'Budget Sensitivity' tab shows in-house/outsourcing activating together once diagnostic headroom exhausts (~£90m ICB-wide), with total reduction plateauing near 98% past that point — a capacity ceiling, not a budget ceiling.

Sheet Assumptions
B2: Model Assumptions
B4: Yellow = key input, edit here (formulas elsewhere reference these cells)
B6: Assumption | C6: Value | D6: Source / flag
B7: ncc_elective_inpatient_cost | C7: 6624 | D7: SOURCED — NHS England National Cost Collection (NCC) 2024/25, National Schedule of NHS costs, Summary: HRG tab, Total row, England-wide (206 providers).
B8: ncc_elective_inpatient_activity | C8: 1255967 | D8: SOURCED — same NCC 2024/25 table, Elective Inpatients activity, Total row. National completion count, used only as the blend weight below.
B9: ncc_daycase_cost | C9: 1078 | D9: SOURCED — same NCC 2024/25 table, Daycase column, Total row.
B10: ncc_daycase_activity | C10: 7680341 | D10: SOURCED — same NCC 2024/25 table, Daycase activity, Total row. National completion count, used only as the blend weight below.
B11: admitted_blended_cost | C11: =($C$7*$C$8+$C$9*$C$10)/($C$8+$C$10) -> 1857.471 | D11: Formula: (elective inpatient cost x its national activity + daycase cost x its national activity) / combined activity. RTT itself does not split "admitted" completions into daycase vs. inpatient, so this ICB's actual daycase/inpatient mix is unknown — bridged using the NCC's own NATIONAL activity mix (daycase is ~86% of national admitted activity) as the best available proxy. Flagged bridging assumption, not a guess at the unit costs themselves, which are real.
B12: ncc_outpatient_procedure_cost | C12: 233 | D12: SOURCED — same NCC 2024/25 table, Outpatient Procedures column, Total row (19,224,707 completions nationally). Used as the proxy for a non-admitted RTT pathway completion.
B13: icb_admitted_share | C13: 0.14742605 | D13: SOURCED from this warehouse, not NCC — the 12 core C&M trusts' own trailing 6-month (Oct-2025 to Mar-2026) real RTT completed_admitted vs. completed_nonadmitted split (fact_rtt_provider_specialty_month). Genuinely this ICB's own mix, not a national figure.
B14: unit_tariff | C14: =$C$13*$C$11+(1-$C$13)*$C$12 -> 472.48935 | D14: Formula: icb_admitted_share x admitted_blended_cost + (1-icb_admitted_share) x outpatient_procedure_cost. Real inputs throughout except the one flagged national-mix bridge above — this REPLACES an earlier flat £1,500 analyst guess with a properly weighted, mostly-sourced figure once Vedant supplied NCC screenshots, 2026-08-08.
B15: c1_inhouse | C15: =$C$14*1 -> 472.48935 | D15: Formula: unit_tariff x 100%. CORRECTED 2026-08-08 — previously 75% based on a 2022 HFMA article describing the 2022/23 ERF scheme, flagged as unverified. Verified against the actual 2025/26 NHS Payment Scheme (NHS England, "NHS provider payment mechanisms"): the marginal-rate mechanism was REMOVED — all elective activity now paid at 100% of NHSPS unit price, no floors/ceilings/marginal rates.
B16: c2_outsource | C16: =$C$14*1 -> 472.48935 | D16: Formula: unit_tariff x 100%. Same 2025/26 NHSPS rate applies equally to independent-sector activity — no policy-driven cost differential from in-house any more, unlike the now-corrected earlier version of this model.
B17: ncc_diagnostic_imaging_cost | C17: 140 | D17: SOURCED — NCC 2024/25, Diagnostic Imaging column, Total row (8,573,583 tests nationally).
B18: ncc_audiology_cost | C18: 107 | D18: SOURCED — NCC 2024/25, Directly Accessed Audiology, Total row (260,367 tests nationally).
B19: ncc_diagnostic_services_cost | C19: 90 | D19: SOURCED — NCC 2024/25, Directly Accessed Diagnostic Services, Total row (6,180,962 tests nationally). Used as the proxy for non-audiology physiological measurement tests (echocardiography, sleep studies, neurophysiology, urodynamics) — DM01 has no more specific NCC match for these.
B20: dm01_imaging_share | C20: 0.79206914 | D20: SOURCED from this warehouse — the 12 core trusts' real DM01 test volume that falls in the 'imaging' category (CT/MRI/ultrasound/DEXA/barium enema), whole warehouse window.
B21: dm01_audiology_share | C21: 0.038054741 | D21: SOURCED — DM01 audiology-assessment share of total test volume, same basis.
B22: dm01_other_physio_share | C22: 0.092408018 | D22: SOURCED — DM01 share for other physiological measurement tests (cardiology, neurophysiology, sleep studies, urodynamics), same basis.
B23: dm01_endoscopy_share | C23: 0.077468099 | D23: SOURCED — DM01 endoscopy share (colonoscopy, gastroscopy, cystoscopy, flexi sigmoidoscopy), same basis. No dedicated NCC "diagnostic test" currency exists for endoscopy — most NHS endoscopies are costed as day-case/outpatient procedures, so Outpatient Procedures is used as the closest real match rather than reusing imaging.
B24: diag_weighted_cost | C24: =$C$20*$C$17+$C$21*$C$18+$C$22*$C$19+$C$23*$C$12 -> 141.32833 | D24: Formula: DM01 category shares x their matched NCC currency cost, summed. Replaces an imaging-only proxy with one reflecting what DM01 actually measures — moves the number only slightly (£140 -> £141) because imaging is ~79% of DM01 volume, which is itself a useful confirmation that the earlier imaging-only proxy was reasonable, not a wasted step.
B25: diag_tests_per_pathway | C25: 1.75 | D25: ANALYST ESTIMATE — the one fully unsourced multiplier left in this model. Plausible clinical assumption (most RTT pathways need at least one diagnostic test before a treatment decision) but not itself a published NHS ratio; no cost dataset would contain this, sourced or not.
B26: c3_diagnostic | C26: =$C$24*$C$25 -> 247.32457 | D26: Formula: diag_weighted_cost x diag_tests_per_pathway. Base cost is now real and DM01-weighted; the tests-per-pathway conversion remains the weakest-sourced figure here.
B27: inhouse_growth_rate | C27: 0.15 | D27: Max in-house capacity growth vs. current trailing 6-month completions. Loosely anchored on a national elective-activity growth ambition cited in 2022/23-era ERF reporting (HFMA) — a growth TARGET, not a payment-mechanism detail, so unaffected by the 2025/26 marginal-rate correction elsewhere on this tab, but also not independently re-verified as current — treat as an analyst planning assumption, +buffer.
B28: diag_growth_rate | C28: 0.1 | D28: Max diagnostic-lever growth vs. current completions — more conservative than in-house, reflecting this is an indirect/bottleneck-relief lever.
B29: is_growth_rate | C29: 0.5 | D29: Assumed independent-sector short-term growth headroom vs. this ICB's current real outsourced RTT volume (sourced from the warehouse itself — see is_trailing_monthly below).
B30: bed_headroom_floor | C30: 0.1 | D30: KH03 G&A bed headroom (%) at/above which a provider faces no extra scaling on its in-house capacity cap; below this, the cap scales down proportionally.
B31: budget_total | C31: 15000000 | D31: SCENARIO INPUT, not a sourced real ICB elective-recovery budget figure — none was publicly available. Change this cell and re-run Solver to see a different allocation.
B32: equity_tolerance_pp | C32: 0.15 | D32: Bounded equity tolerance per Vedant's design steer (2026-08-07): higher-deprivation providers' share of total reduction can fall below their baseline breach share by at most this many percentage points — not a hard no-worsening floor.
B33: higher_baseline_share | C33: ='Provider Inputs'!D21 -> 0.4473947 | D33: Linked from 'Provider Inputs' — higher-deprivation providers' share of total baseline over-52wk breaches.
B34: equity_floor_share | C34: =$C$33-$C$32 -> 0.2973947 | D34: Formula: higher_baseline_share - equity_tolerance_pp — the actual floor used in the Solver equity constraint.
B35: n_months | C35: 18 | D35: Forecast horizon length, months.
B36: is_trailing_monthly | C36: 15019.333 | D36: Real, sourced from the warehouse: this ICB's actual trailing 6-month average monthly independent-sector RTT completed pathways (Mar-2026 warehouse data), NOT an estimate.

Sheet Provider Inputs
B2: 12 Core Providers — Baseline Data & Lever Caps
B3: Green = sourced from nhs_warehouse.db · Black = formula on this sheet
B5: Code | C5: Provider | D5: LA (host) | E5: LA IMD rank | F5: Higher-deprivation? | G5: Baseline over-52wk breaches (18mo) | H5: Trailing monthly completions | I5: Bed headroom % | J5: x1 cap (in-house, /mo) | K5: x2 cap (outsource, /mo) | L5: x3 cap (diagnostic, /mo)
B6: RBL | C6: WIRRAL UNIVERSITY TEACHING HOSPITAL NHS FOUNDATION TRUST | D6: Wirral | E6: 56 | F6: =E6<=$E$18 -> FALSE | G6: 36315.921 | H6: 17334.667 | I6: 0.077429438 | J6: =H6*Assumptions!$C$27*MIN(1,I6/Assumptions!$C$30) -> 2013.3202 | K6: =G6/SUM($G$6:$G$17)*Assumptions!$C$36*Assumptions!$C$29 -> 920.4693 | L6: =H6*Assumptions!$C$28 -> 1733.4667
B7: RBN | C7: MERSEY AND WEST LANCASHIRE TEACHING HOSPITALS NHS TRUST | D7: Knowsley | E7: 3 | F7: =E7<=$E$18 -> TRUE | G7: 57571.8 | H7: 36202.333 | I7: 0.027620374 | J7: =H7*Assumptions!$C$27*MIN(1,I7/Assumptions!$C$30) -> 1499.883 | K7: =G7/SUM($G$6:$G$17)*Assumptions!$C$36*Assumptions!$C$29 -> 1459.2243 | L7: =H7*Assumptions!$C$28 -> 3620.2333
B8: RBQ | C8: LIVERPOOL HEART AND CHEST HOSPITAL NHS FOUNDATION TRUST | D8: Liverpool | E8: 4 | F8: =E8<=$E$18 -> TRUE | G8: 1288.0384 | H8: 3009.3333 | I8: 0.20796179 | J8: =H8*Assumptions!$C$27*MIN(1,I8/Assumptions!$C$30) -> 451.4 | K8: =G8/SUM($G$6:$G$17)*Assumptions!$C$36*Assumptions!$C$29 -> 32.646833 | L8: =H8*Assumptions!$C$28 -> 300.93333
B9: RBS | C9: ALDER HEY CHILDRENS NHS FOUNDATION TRUST | D9: Liverpool | E9: 4 | F9: =E9<=$E$18 -> TRUE | G9: 6840.8135 | H9: 8102 | I9: 0.25144828 | J9: =H9*Assumptions!$C$27*MIN(1,I9/Assumptions!$C$30) -> 1215.3 | K9: =G9/SUM($G$6:$G$17)*Assumptions!$C$36*Assumptions!$C$29 -> 173.38838 | L9: =H9*Assumptions!$C$28 -> 810.2
B10: RBT | C10: MID CHESHIRE HOSPITALS NHS FOUNDATION TRUST | D10: Cheshire East | E10: 131 | F10: =E10<=$E$18 -> FALSE | G10: 33321.375 | H10: 18269.333 | I10: 0.064356324 | J10: =H10*Assumptions!$C$27*MIN(1,I10/Assumptions!$C$30) -> 1763.6207 | K10: =G10/SUM($G$6:$G$17)*Assumptions!$C$36*Assumptions!$C$29 -> 844.56904 | L10: =H10*Assumptions!$C$28 -> 1826.9333
B11: REM | C11: LIVERPOOL UNIVERSITY HOSPITALS NHS FOUNDATION TRUST | D11: Liverpool | E11: 4 | F11: =E11<=$E$18 -> TRUE | G11: 41996.018 | H11: 24960.333 | I11: 0.036652185 | J11: =H11*Assumptions!$C$27*MIN(1,I11/Assumptions!$C$30) -> 1372.2761 | K11: =G11/SUM($G$6:$G$17)*Assumptions!$C$36*Assumptions!$C$29 -> 1064.438 | L11: =H11*Assumptions!$C$28 -> 2496.0333
B12: REN | C12: THE CLATTERBRIDGE CANCER CENTRE NHS FOUNDATION TRUST | D12: Wirral | E12: 56 | F12: =E12<=$E$18 -> FALSE | G12: 0 | H12: 1051.3333 | I12: 0.091578947 | J12: =H12*Assumptions!$C$27*MIN(1,I12/Assumptions!$C$30) -> 144.42 | K12: =G12/SUM($G$6:$G$17)*Assumptions!$C$36*Assumptions!$C$29 -> 0 | L12: =H12*Assumptions!$C$28 -> 105.13333
B13: REP | C13: LIVERPOOL WOMENS NHS FOUNDATION TRUST | D13: Liverpool | E13: 4 | F13: =E13<=$E$18 -> TRUE | G13: 16961.986 | H13: 7333.3333 | I13: 0.37126498 | J13: =H13*Assumptions!$C$27*MIN(1,I13/Assumptions!$C$30) -> 1100 | K13: =G13/SUM($G$6:$G$17)*Assumptions!$C$36*Assumptions!$C$29 -> 429.92129 | L13: =H13*Assumptions!$C$28 -> 733.33333
B14: RET | C14: THE WALTON CENTRE NHS FOUNDATION TRUST | D14: Liverpool | E14: 4 | F14: =E14<=$E$18 -> TRUE | G14: 7897.3002 | H14: 7339.6667 | I14: 0.17827215 | J14: =H14*Assumptions!$C$27*MIN(1,I14/Assumptions!$C$30) -> 1100.95 | K14: =G14/SUM($G$6:$G$17)*Assumptions!$C$36*Assumptions!$C$29 -> 200.16627 | L14: =H14*Assumptions!$C$28 -> 733.96667
B15: RJN | C15: EAST CHESHIRE NHS TRUST | D15: Cheshire East | E15: 131 | F15: =E15<=$E$18 -> FALSE | G15: 19081.145 | H15: 4482 | I15: 0.082918567 | J15: =H15*Assumptions!$C$27*MIN(1,I15/Assumptions!$C$30) -> 557.46152 | K15: =G15/SUM($G$6:$G$17)*Assumptions!$C$36*Assumptions!$C$29 -> 483.63384 | L15: =H15*Assumptions!$C$28 -> 448.2
B16: RJR | C16: COUNTESS OF CHESTER HOSPITAL NHS FOUNDATION TRUST | D16: Cheshire West and Chester | E16: 112 | F16: =E16<=$E$18 -> FALSE | G16: 46245.965 | H16: 15043.667 | I16: 0.0066055943 | J16: =H16*Assumptions!$C$27*MIN(1,I16/Assumptions!$C$30) -> 149.05854 | K16: =G16/SUM($G$6:$G$17)*Assumptions!$C$36*Assumptions!$C$29 -> 1172.1578 | L16: =H16*Assumptions!$C$28 -> 1504.3667
B17: RWW | C17: WARRINGTON AND HALTON TEACHING HOSPITALS NHS FOUNDATION TRUST | D17: Warrington | E17: 109 | F17: =E17<=$E$18 -> FALSE | G17: 28763.785 | H17: 13343.667 | I17: 0.060943018 | J17: =H17*Assumptions!$C$27*MIN(1,I17/Assumptions!$C$30) -> 1219.805 | K17: =G17/SUM($G$6:$G$17)*Assumptions!$C$36*Assumptions!$C$29 -> 729.05162 | L17: =H17*Assumptions!$C$28 -> 1334.3667
C18: MEDIAN LA IMD rank -> | E18: =MEDIAN(E6:E17) -> 30
C20: TOTALS | G20: =SUM(G6:G17) -> 296284.15
C21: Higher-deprivation providers' share of baseline breaches | D21: =SUMIF(F6:F17,TRUE(),G6:G17)/G20 -> 0.4473947

Sheet Solver Model
B2: Solver Model — Decision Variables & Constraints
B3: Blue cells (I:K) are the Solver decision variables — edit directly or let Excel Solver optimize them.
B5: Code | C5: Provider | D5: Higher-dep? | E5: Baseline 18mo | F5: x1 cap/mo | G5: x2 cap/mo | H5: x3 cap/mo | I5: x1 In-house/mo | J5: x2 Outsource/mo | K5: x3 Diagnostic/mo | L5: Reduction 18mo | M5: Residual 18mo | N5: Cost 18mo (£)
B6: ='Provider Inputs'!B6 -> RBL | C6: ='Provider Inputs'!C6 -> WIRRAL UNIVERSITY TEACHING HOSPITAL NHS FOUNDATION TRUST | D6: ='Provider Inputs'!F6 -> FALSE | E6: ='Provider Inputs'!G6 -> 36315.921 | F6: ='Provider Inputs'!J6 -> 2013.3202 | G6: ='Provider Inputs'!K6 -> 920.4693 | H6: ='Provider Inputs'!L6 -> 1733.4667 | I6: 0 | J6: 0 | K6: 0 | L6: =MIN(E6,Assumptions!$C$35*(I6+J6+K6)) -> 0 | M6: =E6-L6 -> 36315.921 | N6: =Assumptions!$C$35*(Assumptions!$C$15*I6+Assumptions!$C$16*J6+Assumptions!$C$26*K6) -> 0
B7: ='Provider Inputs'!B7 -> RBN | C7: ='Provider Inputs'!C7 -> MERSEY AND WEST LANCASHIRE TEACHING HOSPITALS NHS TRUST | D7: ='Provider Inputs'!F7 -> TRUE | E7: ='Provider Inputs'!G7 -> 57571.8 | F7: ='Provider Inputs'!J7 -> 1499.883 | G7: ='Provider Inputs'!K7 -> 1459.2243 | H7: ='Provider Inputs'!L7 -> 3620.2333 | I7: 0 | J7: 0 | K7: 339.30481 | L7: =MIN(E7,Assumptions!$C$35*(I7+J7+K7)) -> 6107.4866 | M7: =E7-L7 -> 51464.313 | N7: =Assumptions!$C$35*(Assumptions!$C$15*I7+Assumptions!$C$16*J7+Assumptions!$C$26*K7) -> 1510531.5
B8: ='Provider Inputs'!B8 -> RBQ | C8: ='Provider Inputs'!C8 -> LIVERPOOL HEART AND CHEST HOSPITAL NHS FOUNDATION TRUST | D8: ='Provider Inputs'!F8 -> TRUE | E8: ='Provider Inputs'!G8 -> 1288.0384 | F8: ='Provider Inputs'!J8 -> 451.4 | G8: ='Provider Inputs'!K8 -> 32.646833 | H8: ='Provider Inputs'!L8 -> 300.93333 | I8: 0 | J8: 0 | K8: 32.646833 | L8: =MIN(E8,Assumptions!$C$35*(I8+J8+K8)) -> 587.64299 | M8: =E8-L8 -> 700.39541 | N8: =Assumptions!$C$35*(Assumptions!$C$15*I8+Assumptions!$C$16*J8+Assumptions!$C$26*K8) -> 145338.55
B9: ='Provider Inputs'!B9 -> RBS | C9: ='Provider Inputs'!C9 -> ALDER HEY CHILDRENS NHS FOUNDATION TRUST | D9: ='Provider Inputs'!F9 -> TRUE | E9: ='Provider Inputs'!G9 -> 6840.8135 | F9: ='Provider Inputs'!J9 -> 1215.3 | G9: ='Provider Inputs'!K9 -> 173.38838 | H9: ='Provider Inputs'!L9 -> 810.2 | I9: 0 | J9: 0 | K9: 0 | L9: =MIN(E9,Assumptions!$C$35*(I9+J9+K9)) -> 0 | M9: =E9-L9 -> 6840.8135 | N9: =Assumptions!$C$35*(Assumptions!$C$15*I9+Assumptions!$C$16*J9+Assumptions!$C$26*K9) -> 0
B10: ='Provider Inputs'!B10 -> RBT | C10: ='Provider Inputs'!C10 -> MID CHESHIRE HOSPITALS NHS FOUNDATION TRUST | D10: ='Provider Inputs'!F10 -> FALSE | E10: ='Provider Inputs'!G10 -> 33321.375 | F10: ='Provider Inputs'!J10 -> 1763.6207 | G10: ='Provider Inputs'!K10 -> 844.56904 | H10: ='Provider Inputs'!L10 -> 1826.9333 | I10: 0 | J10: 0 | K10: 844.56904 | L10: =MIN(E10,Assumptions!$C$35*(I10+J10+K10)) -> 15202.243 | M10: =E10-L10 -> 18119.132 | N10: =Assumptions!$C$35*(Assumptions!$C$15*I10+Assumptions!$C$16*J10+Assumptions!$C$26*K10) -> 3759888.1
B11: ='Provider Inputs'!B11 -> REM | C11: ='Provider Inputs'!C11 -> LIVERPOOL UNIVERSITY HOSPITALS NHS FOUNDATION TRUST | D11: ='Provider Inputs'!F11 -> TRUE | E11: ='Provider Inputs'!G11 -> 41996.018 | F11: ='Provider Inputs'!J11 -> 1372.2761 | G11: ='Provider Inputs'!K11 -> 1064.438 | H11: ='Provider Inputs'!L11 -> 2496.0333 | I11: 0 | J11: 0 | K11: 0 | L11: =MIN(E11,Assumptions!$C$35*(I11+J11+K11)) -> 0 | M11: =E11-L11 -> 41996.018 | N11: =Assumptions!$C$35*(Assumptions!$C$15*I11+Assumptions!$C$16*J11+Assumptions!$C$26*K11) -> 0
B12: ='Provider Inputs'!B12 -> REN | C12: ='Provider Inputs'!C12 -> THE CLATTERBRIDGE CANCER CENTRE NHS FOUNDATION TRUST | D12: ='Provider Inputs'!F12 -> FALSE | E12: ='Provider Inputs'!G12 -> 0 | F12: ='Provider Inputs'!J12 -> 144.42 | G12: ='Provider Inputs'!K12 -> 0 | H12: ='Provider Inputs'!L12 -> 105.13333 | I12: 0 | J12: 0 | K12: 0 | L12: =MIN(E12,Assumptions!$C$35*(I12+J12+K12)) -> 0 | M12: =E12-L12 -> 0 | N12: =Assumptions!$C$35*(Assumptions!$C$15*I12+Assumptions!$C$16*J12+Assumptions!$C$26*K12) -> 0
B13: ='Provider Inputs'!B13 -> REP | C13: ='Provider Inputs'!C13 -> LIVERPOOL WOMENS NHS FOUNDATION TRUST | D13: ='Provider Inputs'!F13 -> TRUE | E13: ='Provider Inputs'!G13 -> 16961.986 | F13: ='Provider Inputs'!J13 -> 1100 | G13: ='Provider Inputs'!K13 -> 429.92129 | H13: ='Provider Inputs'!L13 -> 733.33333 | I13: 0 | J13: 0 | K13: 429.92129 | L13: =MIN(E13,Assumptions!$C$35*(I13+J13+K13)) -> 7738.5831 | M13: =E13-L13 -> 9223.4029 | N13: =Assumptions!$C$35*(Assumptions!$C$15*I13+Assumptions!$C$16*J13+Assumptions!$C$26*K13) -> 1913941.7
B14: ='Provider Inputs'!B14 -> RET | C14: ='Provider Inputs'!C14 -> THE WALTON CENTRE NHS FOUNDATION TRUST | D14: ='Provider Inputs'!F14 -> TRUE | E14: ='Provider Inputs'!G14 -> 7897.3002 | F14: ='Provider Inputs'!J14 -> 1100.95 | G14: ='Provider Inputs'!K14 -> 200.16627 | H14: ='Provider Inputs'!L14 -> 733.96667 | I14: 0 | J14: 0 | K14: 200.16627 | L14: =MIN(E14,Assumptions!$C$35*(I14+J14+K14)) -> 3602.9929 | M14: =E14-L14 -> 4294.3074 | N14: =Assumptions!$C$35*(Assumptions!$C$15*I14+Assumptions!$C$16*J14+Assumptions!$C$26*K14) -> 891108.66
B15: ='Provider Inputs'!B15 -> RJN | C15: ='Provider Inputs'!C15 -> EAST CHESHIRE NHS TRUST | D15: ='Provider Inputs'!F15 -> FALSE | E15: ='Provider Inputs'!G15 -> 19081.145 | F15: ='Provider Inputs'!J15 -> 557.46152 | G15: ='Provider Inputs'!K15 -> 483.63384 | H15: ='Provider Inputs'!L15 -> 448.2 | I15: 0 | J15: 0 | K15: 0 | L15: =MIN(E15,Assumptions!$C$35*(I15+J15+K15)) -> 0 | M15: =E15-L15 -> 19081.145 | N15: =Assumptions!$C$35*(Assumptions!$C$15*I15+Assumptions!$C$16*J15+Assumptions!$C$26*K15) -> 0
B16: ='Provider Inputs'!B16 -> RJR | C16: ='Provider Inputs'!C16 -> COUNTESS OF CHESTER HOSPITAL NHS FOUNDATION TRUST | D16: ='Provider Inputs'!F16 -> FALSE | E16: ='Provider Inputs'!G16 -> 46245.965 | F16: ='Provider Inputs'!J16 -> 149.05854 | G16: ='Provider Inputs'!K16 -> 1172.1578 | H16: ='Provider Inputs'!L16 -> 1504.3667 | I16: 0 | J16: 0 | K16: 1172.1578 | L16: =MIN(E16,Assumptions!$C$35*(I16+J16+K16)) -> 21098.841 | M16: =E16-L16 -> 25147.124 | N16: =Assumptions!$C$35*(Assumptions!$C$15*I16+Assumptions!$C$16*J16+Assumptions!$C$26*K16) -> 5218261.7
B17: ='Provider Inputs'!B17 -> RWW | C17: ='Provider Inputs'!C17 -> WARRINGTON AND HALTON TEACHING HOSPITALS NHS FOUNDATION TRUST | D17: ='Provider Inputs'!F17 -> FALSE | E17: ='Provider Inputs'!G17 -> 28763.785 | F17: ='Provider Inputs'!J17 -> 1219.805 | G17: ='Provider Inputs'!K17 -> 729.05162 | H17: ='Provider Inputs'!L17 -> 1334.3667 | I17: 0 | J17: 0 | K17: 350.62556 | L17: =MIN(E17,Assumptions!$C$35*(I17+J17+K17)) -> 6311.26 | M17: =E17-L17 -> 22452.525 | N17: =Assumptions!$C$35*(Assumptions!$C$15*I17+Assumptions!$C$16*J17+Assumptions!$C$26*K17) -> 1560929.7
C19: TOTAL / OBJECTIVE | E19: =SUM(E6:E17) -> 296284.15 | L19: =SUM(L6:L17) -> 60649.049 | M19: =SUM(M6:M17) -> 235635.1 | N19: =SUM(N6:N17) -> 15000000
C21: Objective cell (Solver: Set Objective, To: Max) | E21: =L19 -> 60649.049
C22: % of baseline breaches eliminated | E22: =L19/E19 -> 0.20469893
C23: Total cost (18mo, £) | E23: =N19 -> 15000000
C24: Budget (£) — constraint: cost <= budget | E24: =Assumptions!$C$31 -> 15000000
C25: Budget slack (must be >= 0) | E25: =E24-N19 -> 0
C26: Higher-deprivation providers' reduction | E26: =SUMIF(D6:D17,TRUE(),L6:L17) -> 18036.706
C27: Equity floor share (of total reduction) | E27: =Assumptions!$C$34 -> 0.2973947
C28: Equity check cell (must be >= 0) | E28: =E26-E27*L19 -> -3.6379788e-11
B31: Excel Solver setup (Data > Solver — enable via File > Options > Add-ins if not visible)
B32: • Set Objective: $L19 -> To: Max
B33: • By Changing Variable Cells: $I$6:$K$17
B34: • Constraint 1 (budget): $N19 <= $E24
B35: • Constraint 2 (equity): $E28 >= 0
B36: • Constraint 3 (in-house cap): $I$6:$I$17 <= $E$6:$E$17
B37: • Constraint 4 (outsource cap): $J$6:$J$17 <= $F$6:$F$17
B38: • Constraint 5 (diagnostic cap): $K$6:$K$17 <= $G$6:$G$17
B39: • Constraint 6 (non-negativity): $I$6:$K$17 >= 0
B40: • Solving Method: Simplex LP (this is a linear program — GRG Nonlinear will also work but is slower and unnecessary)
B41: • Click Solve. Excel's Solver should converge to the same objective value already shown in the pre-filled cells above (a Python/scipy reference solve of the identical LP) — if it doesn't, something in the constraint setup above was mistyped, not a modeling error.

Sheet Budget Sensitivity
B2: Budget Sensitivity — 9-point sweep (reference Python solves, not live formulas)
B3: Shows which lever activates at which budget level. Re-solved independently per budget with scipy — read-only reference, not Solver-linked.
B5: Budget (£, 18mo) | C5: In-house units (18mo) | D5: Outsource units (18mo) | E5: Diagnostic units (18mo) | F5: Total reduction (breaches) | G5: % baseline eliminated
B6: 2000000 | C6: 0 | D6: 0 | E6: 8086.5399 | F6: 8086.5399 | G6: 0.027293191
B7: 5000000 | C7: 0 | D7: 0 | E7: 20216.35 | F7: 20216.35 | G7: 0.068232978
B8: 10000000 | C8: 0 | D8: 0 | E8: 40432.699 | F8: 40432.699 | G8: 0.13646596
B9: 15000000 | C9: 0 | D9: 0 | E9: 60649.049 | F9: 60649.049 | G9: 0.20469893
B10: 25000000 | C10: 0 | D10: 0 | E10: 101081.75 | F10: 101081.75 | G10: 0.34116489
B11: 40000000 | C11: 0 | D11: 0 | E11: 161730.8 | F11: 161730.8 | G11: 0.54586383
B12: 60000000 | C12: 0 | D12: 0 | E12: 242596.2 | F12: 242596.2 | G12: 0.81879574
B13: 90000000 | C13: 41488.399 | D13: 39294.641 | E13: 209566.22 | F13: 290349.26 | G13: 0.97996892
B14: 130000000 | C14: 63095.845 | D14: 39294.641 | E14: 187958.77 | F14: 290349.26 | G14: 0.97996892
B41: Reading this (real NCC costs + the 2025/26 payment-scheme correction that made in-house and outsourcing cost the SAME): diagnostics (£247/unit) fills first as budget rises since it's structurally cheaper, then in-house and outsourcing (both £472/unit — genuinely tied on cost now, not one preferred over the other) activate together once diagnostic headroom exhausts around £90m ICB-wide, simply because they're the two remaining levers with capacity left. Beyond that point, total reduction plateaus around 98% regardless of further budget: every lever's CAPACITY ceiling (workforce/bed headroom, outsourcing pool) is now the binding constraint, not money. Below £90m this is a budget problem; above it, a capacity problem.
